cli/__init__.py
cli/__main__.py
cli/uploader.py
lib/__init__.py
lib/models.py
fulcrum_cli-0.1.1.dist-info/METADATA
fulcrum_cli-0.1.1.dist-info/WHEEL
fulcrum_cli-0.1.1.dist-info/entry_points.txt
fulcrum_cli-0.1.1.dist-info/top_level.txt
fulcrum_cli-0.1.1.dist-info/RECORD
