Metadata-Version: 2.4
Name: fulcrum-cli
Version: 0.1.1
Summary: Utility to connect and use Fulcrum Research to understand your agents
Author-email: Uzay Girit <uzay@fulcrumresearch.ai>
Keywords: observability,ai,agents
Classifier: Programming Language :: Python :: 3
Requires-Python: >=3.10
Requires-Dist: inspect-ai>=0.3.122
Requires-Dist: pydantic>=2.11.7
Requires-Dist: requests
Requires-Dist: python-dotenv
